{
  "$schema": "https://developer.microsoft.com/json-schemas/fabric/item/report/definition/visualContainer/2.5.0/schema.json",
  "name": "d477b2b037fd0cf3b349",
  "position": {
    "x": 1325,
    "y": 740,
    "z": 13000,
    "height": 465,
    "width": 615,
    "tabOrder": 12000
  },
  "visual": {
    "visualType": "areaChart",
    "query": {
      "queryState": {
        "Category": {
          "projections": [
            {
              "field": {
                "Column": {
                  "Expression": {
                    "SourceRef": {
                      "Entity": "hotel_booking"
                    }
                  },
                  "Property": "Stay_type"
                }
              },
              "queryRef": "hotel_booking.Stay_type",
              "nativeQueryRef": "Stay_type",
              "active": true
            },
            {
              "field": {
                "Column": {
                  "Expression": {
                    "SourceRef": {
                      "Entity": "hotel_booking"
                    }
                  },
                  "Property": "arrival_date_week_number"
                }
              },
              "queryRef": "hotel_booking.arrival_date_week_number",
              "nativeQueryRef": "arrival_date_week_number",
              "active": true
            }
          ]
        },
        "Y": {
          "projections": [
            {
              "field": {
                "Measure": {
                  "Expression": {
                    "SourceRef": {
                      "Entity": "hotel_booking"
                    }
                  },
                  "Property": "Total Bookings"
                }
              },
              "queryRef": "hotel_booking.Total Bookings",
              "nativeQueryRef": "Total Bookings"
            }
          ]
        }
      },
      "sortDefinition": {
        "sort": [
          {
            "field": {
              "Column": {
                "Expression": {
                  "SourceRef": {
                    "Entity": "hotel_booking"
                  }
                },
                "Property": "Stay_type"
              }
            },
            "direction": "Ascending"
          },
          {
            "field": {
              "Column": {
                "Expression": {
                  "SourceRef": {
                    "Entity": "hotel_booking"
                  }
                },
                "Property": "arrival_date_week_number"
              }
            },
            "direction": "Ascending"
          }
        ],
        "isDefaultSort": true
      }
    },
    "objects": {
      "valueAxis": [
        {
          "properties": {
            "fontSize": {
              "expr": {
                "Literal": {
                  "Value": "23D"
                }
              }
            },
            "titleFontSize": {
              "expr": {
                "Literal": {
                  "Value": "20D"
                }
              }
            }
          }
        }
      ],
      "labels": [
        {
          "properties": {
            "show": {
              "expr": {
                "Literal": {
                  "Value": "false"
                }
              }
            }
          }
        }
      ]
    },
    "visualContainerObjects": {
      "background": [
        {
          "properties": {
            "color": {
              "solid": {
                "color": {
                  "expr": {
                    "ThemeDataColor": {
                      "ColorId": 2,
                      "Percent": 0.6
                    }
                  }
                }
              }
            }
          }
        }
      ],
      "dropShadow": [
        {
          "properties": {
            "show": {
              "expr": {
                "Literal": {
                  "Value": "true"
                }
              }
            },
            "position": {
              "expr": {
                "Literal": {
                  "Value": "'Inner'"
                }
              }
            }
          }
        }
      ],
      "border": [
        {
          "properties": {
            "show": {
              "expr": {
                "Literal": {
                  "Value": "true"
                }
              }
            },
            "radius": {
              "expr": {
                "Literal": {
                  "Value": "9D"
                }
              }
            }
          }
        }
      ]
    },
    "drillFilterOtherVisuals": true
  }
}